jiechau_mcp_vincent_says/__init__.py
jiechau_mcp_vincent_says-0.1.1.dist-info/WHEEL
jiechau_mcp_vincent_says-0.1.1.dist-info/entry_points.txt
jiechau_mcp_vincent_says-0.1.1.dist-info/METADATA
jiechau_mcp_vincent_says-0.1.1.dist-info/RECORD
