Metadata-Version: 2.3
Name: jiechau-mcp-vincent-says
Version: 0.1.1
Summary: You always have something to ask Vincent—anything, everything—you just want to know how Vincent would say it. So, let’s ask Vincent
Author: jiechau
Author-email: jiechau <jiechau@gmail.com>
Requires-Dist: mcp[cli]>=1.13.1
Requires-Python: >=3.13
Project-URL: Homepage, https://gitlab.com/jiechau/jiechau_mcp_vincent_says
